Workbook

Sheet Orders
A1: order_id | B1: order_date | C1: branch | D1: region | E1: product | F1: category | G1: channel | H1: units_sold | I1: unit_price | J1: revenue | K1: month | L1: weekday | M1: is_weekend | N1: price_band
A2: DUKA-0001 | B2: 2026-03-24 | C2: Mombasa | D2: Coast | E2: Smart Watch | F2: Wearables | G2: Online | H2: 1 | I2: 23100 | J2: 23100 | K2: March | L2: Tuesday | M2: FALSE | N2: Value
A3: DUKA-0002 | B3: 2026-06-07 | C3: Nairobi | D3: Capital | E3: Laptop Pro 14 | F3: Computing | G3: In-store | H3: 4 | I3: 118900 | J3: 475600 | K3: June | L3: Sunday | M3: TRUE | N3: Premium
A4: DUKA-0003 | B4: 2026-05-15 | C4: Nairobi | D4: Capital | E4: Smartphone X | F4: Mobile | G4: In-store | H4: 2 | I4: 39700 | J4: 79400 | K4: May | L4: Friday | M4: FALSE | N4: Premium
A5: DUKA-0004 | B5: 2026-02-18 | C5: Thika | D5: Central | E5: HD Television 32in | F5: Television | G5: In-store | H5: 3 | I5: 26600 | J5: 79800 | K5: February | L5: Wednesday | M5: FALSE | N5: Value
A6: DUKA-0005 | B6: 2026-04-16 | C6: Kisumu | D6: Western | E6: Wireless Headphones | F6: Audio | G6: In-store | H6: 1 | I6: 8400 | J6: 8400 | K6: April | L6: Thursday | M6: FALSE | N6: Value
A7: DUKA-0006 | B7: 2026-06-11 | C7: Nakuru | D7: Rift Valley | E7: Bluetooth Speaker | F7: Audio | G7: Online | H7: 1 | I7: 7000 | J7: 7000 | K7: June | L7: Thursday | M7: FALSE | N7: Value
A8: DUKA-0007 | B8: 2026-06-21 | C8: Nairobi | D8: Capital | E8: Smartphone X | F8: Mobile | G8: In-store | H8: 1 | I8: 44300 | J8: 44300 | K8: June | L8: Sunday | M8: TRUE | N8: Premium
A9: DUKA-0008 | B9: 2026-02-25 | C9: Westlands | D9: Capital | E9: Wireless Headphones | F9: Audio | G9: In-store | H9: 1 | I9: 8100 | J9: 8100 | K9: February | L9: Wednesday | M9: FALSE | N9: Value
A10: DUKA-0009 | B10: 2026-02-25 | C10: Eldoret | D10: Rift Valley | E10: HD Television 32in | F10: Television | G10: In-store | H10: 2 | I10: 29700 | J10: 59400 | K10: February | L10: Wednesday | M10: FALSE | N10: Premium
A11: DUKA-0010 | B11: 2026-01-11 | C11: Eldoret | D11: Rift Valley | E11: Wireless Headphones | F11: Audio | G11: Online | H11: 3 | I11: 7900 | J11: 23700 | K11: January | L11: Sunday | M11: TRUE | N11: Value
A12: DUKA-0011 | B12: 2026-05-19 | C12: Nyeri | D12: Central | E12: Power Bank 20K | F12: Accessories | G12: In-store | H12: 2 | I12: 4700 | J12: 9400 | K12: May | L12: Tuesday | M12: FALSE | N12: Value
A13: DUKA-0012 | B13: 2026-02-22 | C13: Westlands | D13: Capital | E13: Power Bank 20K | F13: Accessories | G13: Online | H13: 1 | I13: 4300 | J13: 4300 | K13: February | L13: Sunday | M13: TRUE | N13: Value
... A1001: DUKA-1000 | B1001: 2026-03-23 | C1001: Westlands | D1001: Capital | E1001: Budget Smartphone | F1001: Mobile | G1001: In-store | H1001: 1 | I1001: 19600 | J1001: 19600 | K1001: March | L1001: Monday | M1001: FALSE | N1001: Value

Sheet Region Lookup
A1: branch | B1: region
A2: Eldoret | B2: Rift Valley
A3: Kisumu | B3: Western
A4: Mombasa | B4: Coast
A5: Nairobi | B5: Capital
A6: Nakuru | B6: Rift Valley
A7: Nyeri | B7: Central
A8: Thika | B8: Central
A9: Westlands | B9: Capital

Sheet Branch Summary
A1: branch | B1: revenue_kes | C1: region | D1: orders
A2: Mombasa | B2: =SUMIFS(Orders!$J:$J,Orders!$C:$C,A2) -> 8180000 | C2: =IFERROR(_xludf.XLOOKUP(A2,'Region Lookup'!$A$2:$A$9,'Region Lookup'!$B$2:$B$9,"Not found"),VLOOKUP(A2,'Region Lookup'!$A$2:$B$9,2,FALSE)) -> Coast | D2: =COUNTIF(Orders!$C:$C,A2) -> 132
A3: Nakuru | B3: =SUMIFS(Orders!$J:$J,Orders!$C:$C,A3) -> 6860500 | C3: =IFERROR(_xludf.XLOOKUP(A3,'Region Lookup'!$A$2:$A$9,'Region Lookup'!$B$2:$B$9,"Not found"),VLOOKUP(A3,'Region Lookup'!$A$2:$B$9,2,FALSE)) -> Rift Valley | D3: =COUNTIF(Orders!$C:$C,A3) -> 127
A4: Nairobi | B4: =SUMIFS(Orders!$J:$J,Orders!$C:$C,A4) -> 6775000 | C4: =IFERROR(_xludf.XLOOKUP(A4,'Region Lookup'!$A$2:$A$9,'Region Lookup'!$B$2:$B$9,"Not found"),VLOOKUP(A4,'Region Lookup'!$A$2:$B$9,2,FALSE)) -> Capital | D4: =COUNTIF(Orders!$C:$C,A4) -> 121
A5: Kisumu | B5: =SUMIFS(Orders!$J:$J,Orders!$C:$C,A5) -> 6671800 | C5: =IFERROR(_xludf.XLOOKUP(A5,'Region Lookup'!$A$2:$A$9,'Region Lookup'!$B$2:$B$9,"Not found"),VLOOKUP(A5,'Region Lookup'!$A$2:$B$9,2,FALSE)) -> Western | D5: =COUNTIF(Orders!$C:$C,A5) -> 120
A6: Westlands | B6: =SUMIFS(Orders!$J:$J,Orders!$C:$C,A6) -> 6605900 | C6: =IFERROR(_xludf.XLOOKUP(A6,'Region Lookup'!$A$2:$A$9,'Region Lookup'!$B$2:$B$9,"Not found"),VLOOKUP(A6,'Region Lookup'!$A$2:$B$9,2,FALSE)) -> Capital | D6: =COUNTIF(Orders!$C:$C,A6) -> 118
A7: Nyeri | B7: =SUMIFS(Orders!$J:$J,Orders!$C:$C,A7) -> 6558700 | C7: =IFERROR(_xludf.XLOOKUP(A7,'Region Lookup'!$A$2:$A$9,'Region Lookup'!$B$2:$B$9,"Not found"),VLOOKUP(A7,'Region Lookup'!$A$2:$B$9,2,FALSE)) -> Central | D7: =COUNTIF(Orders!$C:$C,A7) -> 136
A8: Eldoret | B8: =SUMIFS(Orders!$J:$J,Orders!$C:$C,A8) -> 5885500 | C8: =IFERROR(_xludf.XLOOKUP(A8,'Region Lookup'!$A$2:$A$9,'Region Lookup'!$B$2:$B$9,"Not found"),VLOOKUP(A8,'Region Lookup'!$A$2:$B$9,2,FALSE)) -> Rift Valley | D8: =COUNTIF(Orders!$C:$C,A8) -> 137
A9: Thika | B9: =SUMIFS(Orders!$J:$J,Orders!$C:$C,A9) -> 4926700 | C9: =IFERROR(_xludf.XLOOKUP(A9,'Region Lookup'!$A$2:$A$9,'Region Lookup'!$B$2:$B$9,"Not found"),VLOOKUP(A9,'Region Lookup'!$A$2:$B$9,2,FALSE)) -> Central | D9: =COUNTIF(Orders!$C:$C,A9) -> 109

Sheet PivotTable
A1: Revenue by branch and channel
A2: Generated as an Excel PivotTable from the Orders sheet when this notebook runs on Windows with Excel installed.
A4: Revenue (KES) | B4: channel
A5: branch | B5: In-store | C5: Online | D5: Grand Total
A6: Eldoret | B6: 3979000 | C6: 1906500 | D6: 5885500
A7: Kisumu | B7: 4678900 | C7: 1992900 | D7: 6671800
A8: Mombasa | B8: 3878600 | C8: 4301400 | D8: 8180000
A9: Nairobi | B9: 4812700 | C9: 1962300 | D9: 6775000
A10: Nakuru | B10: 3843400 | C10: 3017100 | D10: 6860500
A11: Nyeri | B11: 3825000 | C11: 2733700 | D11: 6558700
A12: Thika | B12: 3242500 | C12: 1684200 | D12: 4926700
A13: Westlands | B13: 4705900 | C13: 1900000 | D13: 6605900
A14: Grand Total | B14: 32966000 | C14: 19498100 | D14: 52464100
